sbatch_paramfile/__init__.py
sbatch_paramfile/main.py
sbatch_paramfile-0.1.1.dist-info/METADATA
sbatch_paramfile-0.1.1.dist-info/WHEEL
sbatch_paramfile-0.1.1.dist-info/entry_points.txt
sbatch_paramfile-0.1.1.dist-info/top_level.txt
sbatch_paramfile-0.1.1.dist-info/RECORD
