Metadata-Version: 2.1
Name: sbatch_paramfile
Version: 0.1.1
Summary: A command line tool to create a sbatch file for a parameter file
Home-page: https://github.com/WissamAntoun/sbatch_paramfile
Author: Wissam Antoun
Author-email: wissam.antoun@gmail.com
Classifier: Development Status :: 5 - Production/Stable
Classifier: Intended Audience :: Developers
Classifier: Intended Audience :: Education
Classifier: Intended Audience :: Science/Research
Classifier: Operating System :: OS Independent
Classifier: Programming Language :: Python :: 3
Classifier: Programming Language :: Python :: 3.6
Classifier: Programming Language :: Python :: 3.7
Classifier: Programming Language :: Python :: 3.8
Classifier: Programming Language :: Python :: 3.9
Classifier: Programming Language :: Python :: 3.10
Classifier: Topic :: Scientific/Engineering
Requires-Python: >=3.6.0
